setup.cfg
setup.py
./bkapi/__init__.py
./bkapi/bcs_api_gateway/__init__.py
./bkapi/bcs_api_gateway/client.py
./bkapi/bcs_api_gateway/client.pyi
./bkapi/bcs_api_gateway/shortcuts.py
./bkapigw/__init__.py
./bkapigw/bcs_api_gateway/__init__.py
./bkapigw/bcs_api_gateway/base.py
./bkapigw/bcs_api_gateway/client.py
./bkapigw/bcs_api_gateway/conf.py
./bkapigw/bcs_api_gateway/exceptions.py
./bkapigw/bcs_api_gateway/resources.py
./bkapigw/bcs_api_gateway/shortcuts.py
./bkapigw/bcs_api_gateway/utils.py
bkapi_bcs_api_gateway.egg-info/PKG-INFO
bkapi_bcs_api_gateway.egg-info/SOURCES.txt
bkapi_bcs_api_gateway.egg-info/dependency_links.txt
bkapi_bcs_api_gateway.egg-info/namespace_packages.txt
bkapi_bcs_api_gateway.egg-info/requires.txt
bkapi_bcs_api_gateway.egg-info/top_level.txt