Metadata-Version: 2.1
Name: bkapi-bcs-api-gateway
Version: 1.12.1
Summary: bk-bcs容器化部署方案api-gateway
Home-page: UNKNOWN
Author: blueking
License: Apach License 2.0
Platform: UNKNOWN
Requires-Python: !=3.0.*,!=3.1.*,!=3.2.*,!=3.3.*,!=3.4.*,!=3.5.*,<4.0,>=2.7
Provides-Extra: django
